parking_lot/index.py
parking_lot-1.0.3.dist-info/LICENSE
parking_lot-1.0.3.dist-info/METADATA
parking_lot-1.0.3.dist-info/WHEEL
parking_lot-1.0.3.dist-info/entry_points.txt
parking_lot-1.0.3.dist-info/top_level.txt
parking_lot-1.0.3.dist-info/RECORD
