Metadata-Version: 2.1
Name: parking-lot
Version: 1.0.3
Summary: A Python package to which allocate parking slot for Car.
Home-page: UNKNOWN
Author: Shubham Gupta
Author-email: gshubham934@gmail.com
License: MIT
Platform: UNKNOWN
Classifier: License :: OSI Approved :: MIT License
Classifier: Programming Language :: Python :: 3
Classifier: Programming Language :: Python :: 3.7
Requires-Dist: colorama
